ec2hashcat
