Metadata-Version: 1.1
Name: ec2hashcat
Version: 1.0.2
Summary: Password Cracking in the Cloud
Home-page: https://www.github.com/wrboyce/ec2hashcat
Author: Will Boyce
Author-email: me@willboyce.com
License: License :: OSI Approved :: Apache Software License
Platform: Operating System :: MacOS :: MacOS X
Platform: Operating System :: POSIX
Classifier: Development Status :: 5 - Production/Stable
Classifier: Environment :: Console
Classifier: License :: OSI Approved :: Apache Software License
Classifier: Operating System :: MacOS :: MacOS X
Classifier: Operating System :: POSIX
Classifier: Programming Language :: Python :: 2.7
Classifier: Topic :: Security
